{
	"format_version": "1.12.0",
	"minecraft:geometry": [
		{
			"description": {
				"identifier": "geometry.beacon",
				"texture_width": 128,
				"texture_height": 64,
				"visible_bounds_width": 3,
				"visible_bounds_height": 3.5,
				"visible_bounds_offset": [0, 1.25, 0]
			},
			"bones": [
				{
					"name": "beacon",
					"pivot": [0, 0, 0],
					"cubes": [
						{"origin": [-8, 0, -8], "size": [16, 4, 16], "uv": [56, 0]}
					]
				},
				{
					"name": "core",
					"parent": "beacon",
					"pivot": [0, 11, 0],
					"cubes": [
						{"origin": [-7, 4, -7], "size": [14, 14, 14], "uv": [0, 0]},
						{"origin": [-9, 2.1, -9], "size": [18, 18, 18], "inflate": 1, "uv": [0, 28]}
					]
				}
			]
		}
	]
}